memhax/__init__.py
memhax/element.py
memhax/utils.py
memhax/cpython/__init__.py
memhax/cpython/collections.py
memhax/cpython/object.py
memhax/cpython/primitives.py
memhax/cpython/type_attributes.py
memhax/native/__init__.py
memhax/native/native.py
memhax/native/native_complex.py
memhax/native/native_size.py
memhax/native/structs.py
memhax-0.1.0.dist-info/LICENSE
memhax-0.1.0.dist-info/METADATA
memhax-0.1.0.dist-info/WHEEL
memhax-0.1.0.dist-info/top_level.txt
memhax-0.1.0.dist-info/RECORD
