Metadata-Version: 2.1
Name: memhax
Version: 0.1.0
Summary: A Python library for getting access to raw memory and internals
Classifier: Development Status :: 4 - Beta
Classifier: Programming Language :: Python :: 3.11
Classifier: Programming Language :: Python :: Implementation :: CPython
Classifier: Operating System :: Unix
Classifier: Intended Audience :: Developers
Classifier: License :: OSI Approved :: BSD License
Classifier: Typing :: Typed
Requires-Python: >=3.11,<3.12
License-File: LICENSE
